LICENSE
MANIFEST.in
README.rst
midas_girder_connection.py
setup.py
girder_tech_journal/__init__.py
girder_tech_journal/constants.py
girder_tech_journal/settings.py
girder_tech_journal.egg-info/PKG-INFO
girder_tech_journal.egg-info/SOURCES.txt
girder_tech_journal.egg-info/dependency_links.txt
girder_tech_journal.egg-info/entry_points.txt
girder_tech_journal.egg-info/requires.txt
girder_tech_journal.egg-info/top_level.txt
girder_tech_journal/api/__init__.py
girder_tech_journal/api/tech_journal.py
girder_tech_journal/external_web_client/favicon.ico
girder_tech_journal/external_web_client/index.html
girder_tech_journal/external_web_client/css/app.e94c34da.css
girder_tech_journal/external_web_client/css/chunk-vendors.faff628b.css
girder_tech_journal/external_web_client/dist/favicon.ico
girder_tech_journal/external_web_client/dist/index.html
girder_tech_journal/external_web_client/dist/css/app.a5ee6c24.css
girder_tech_journal/external_web_client/dist/css/app.e94c34da.css
girder_tech_journal/external_web_client/dist/css/chunk-vendors.faff628b.css
girder_tech_journal/external_web_client/dist/fonts/fontello.09b09701.woff
girder_tech_journal/external_web_client/dist/fonts/fontello.4e544c77.eot
girder_tech_journal/external_web_client/dist/fonts/fontello.8891ff67.woff2
girder_tech_journal/external_web_client/dist/fonts/fontello.cb8f1e44.ttf
girder_tech_journal/external_web_client/dist/fonts/glyphicons-halflings-regular.448c34a5.woff2
girder_tech_journal/external_web_client/dist/fonts/glyphicons-halflings-regular.e18bbf61.ttf
girder_tech_journal/external_web_client/dist/fonts/glyphicons-halflings-regular.f4769f9b.eot
girder_tech_journal/external_web_client/dist/fonts/glyphicons-halflings-regular.fa277232.woff
girder_tech_journal/external_web_client/dist/fonts/open-sans-latin-300.521d17bc.woff
girder_tech_journal/external_web_client/dist/fonts/open-sans-latin-300.60c86674.woff2
girder_tech_journal/external_web_client/dist/fonts/open-sans-latin-300italic.06bbd318.woff2
girder_tech_journal/external_web_client/dist/fonts/open-sans-latin-300italic.8a648ff3.woff
girder_tech_journal/external_web_client/dist/fonts/open-sans-latin-400.bf2d0783.woff
girder_tech_journal/external_web_client/dist/fonts/open-sans-latin-400.cffb686d.woff2
